README.txt
setup.py
f5abtesting/__init__.py
f5abtesting/abtesting.py
f5abtesting/abtesting_cli.py
f5abtesting/f5sdk_pool_patch.py
f5abtesting/ip2region.conf
f5abtesting/irules_tmp.conf
f5abtesting.egg-info/PKG-INFO
f5abtesting.egg-info/SOURCES.txt
f5abtesting.egg-info/dependency_links.txt
f5abtesting.egg-info/requires.txt
f5abtesting.egg-info/top_level.txt