Metadata-Version: 1.0
Name: f5abtesting
Version: 0.1.4
Summary: A python package for region based abtesting
Home-page: https://github.com/xp2014/f5abtesting
Author: Ping Xiong
Author-email: p.xiong@f5.com
License: Apache License, Version 2.0
Platform: UNKNOWN
